AUTHORS.rst
CONTRIBUTING.rst
HISTORY.rst
LICENSE
MANIFEST.in
README.rst
setup.cfg
setup.py
riso_banking/__init__.py
riso_banking/admin.py
riso_banking/apps.py
riso_banking/models.py
riso_banking/urls.py
riso_banking/views.py
riso_banking.egg-info/PKG-INFO
riso_banking.egg-info/SOURCES.txt
riso_banking.egg-info/dependency_links.txt
riso_banking.egg-info/not-zip-safe
riso_banking.egg-info/requires.txt
riso_banking.egg-info/top_level.txt
riso_banking/static/css/riso_banking.css
riso_banking/static/js/riso_banking.js
riso_banking/templates/riso_banking/base.html
riso_banking/test_utils/__init__.py
riso_banking/test_utils/test_app/__init__.py
riso_banking/test_utils/test_app/admin.py
riso_banking/test_utils/test_app/apps.py
riso_banking/test_utils/test_app/models.py
riso_banking/test_utils/test_app/migrations/__init__.py