Metadata-Version: 1.1
Name: riso-banking
Version: 0.1.0
Summary: Riso Banking System
Home-page: https://github.com/riso-tech/riso-banking
Author: Bin Nguyen
Author-email: support@risotech.vn
License: MIT
Keywords: riso-banking
Platform: UNKNOWN
Classifier: Development Status :: 3 - Alpha
Classifier: Framework :: Django :: 3.1
Classifier: Intended Audience :: Developers
Classifier: License :: OSI Approved :: BSD License
Classifier: Natural Language :: English
Classifier: Programming Language :: Python :: 2
Classifier: Programming Language :: Python :: 2.7
Classifier: Programming Language :: Python :: 3
Classifier: Programming Language :: Python :: 3.5
Classifier: Programming Language :: Python :: 3.6
Classifier: Programming Language :: Python :: 3.7
Classifier: Programming Language :: Python :: 3.8
